bcml4pheno/__init__.py
bcml4pheno/_nbdev.py
bcml4pheno/bcml_model.py
bcml4pheno/data_vis.py
bcml4pheno/manual_opt.py
bcml4pheno/ttbarzp.py
bcml4pheno-0.0.9.dist-info/LICENSE
bcml4pheno-0.0.9.dist-info/METADATA
bcml4pheno-0.0.9.dist-info/WHEEL
bcml4pheno-0.0.9.dist-info/top_level.txt
bcml4pheno-0.0.9.dist-info/RECORD
