Metadata-Version: 2.1
Name: bcml4pheno
Version: 0.0.9
Summary: Library for conducting, evaluating, and visualizing binary classification machine learning models for physics phenomenology.
Home-page: https://github.com/sheride/bcml4pheno/tree/master/
Author: Elijah Sheridan
Author-email: elijah.sheridan@vanderbilt.edu
License: Apache Software License 2.0
Keywords: ML classification physics phenomenology
Platform: UNKNOWN
Classifier: Development Status :: 3 - Alpha
Classifier: Intended Audience :: Developers
Classifier: Natural Language :: English
Classifier: Programming Language :: Python :: 3.6
Classifier: Programming Language :: Python :: 3.7
Classifier: Programming Language :: Python :: 3.8
Classifier: License :: OSI Approved :: Apache Software License
Requires-Python: >=3.6
License-File: LICENSE
Requires-Dist: pip
Requires-Dist: packaging
Requires-Dist: numpy
Requires-Dist: scipy
Requires-Dist: matplotlib
Requires-Dist: scikit-learn
Requires-Dist: pandas
Requires-Dist: joblib
Requires-Dist: datetime
Requires-Dist: xgboost
Provides-Extra: dev
